{
  "potentialMembers": [
    {
      "clubId": "local-001",
      "contacts": [
        {
          "id": "pm-008",
          "firstName": "Greg",
          "lastName": "Harmon",
          "email": "g.harmon@gmail.com",
          "phone": "941-555-0331",
          "contactDate": "2026-07-05",
          "source": "CLUB",
          "responded": false,
          "respondedDate": null,
          "message": {
            "isMember": false,
            "interest": "Competitive swimming",
            "body": "I swam through high school and college and just turned 30 — ready to get back into competition. Do you have a structured program for returning swimmers who want to race again?"
          }
        },
        {
          "id": "pm-009",
          "firstName": "Priya",
          "lastName": "Sharma",
          "email": "priya.sharma@icloud.com",
          "phone": "",
          "contactDate": "2026-07-02",
          "source": "CLUB",
          "responded": false,
          "respondedDate": null,
          "message": {
            "isMember": false,
            "interest": "Fitness swimming",
            "body": "I've been swimming on my own for two years and would love to join a group for accountability and coaching. Are your practices open to all ability levels, or is it primarily competitive?"
          }
        },
        {
          "id": "pm-010",
          "firstName": "Marcus",
          "lastName": "Webb",
          "email": "mwebb@outlook.com",
          "phone": "727-555-0819",
          "contactDate": "2026-06-28",
          "source": "TMS",
          "responded": false,
          "respondedDate": null,
          "message": {
            "isMember": false,
            "interest": "Triathlon training",
            "body": "I picked up a USMS trial membership while training for my first sprint tri. I need help with open turns and flip turns more than anything. Does your club do any technique-focused workouts?"
          }
        },
        {
          "id": "pm-011",
          "firstName": "Carla",
          "lastName": "Figueroa",
          "email": "carla.figueroa@gmail.com",
          "phone": "813-555-0574",
          "contactDate": "2026-06-22",
          "source": "CLUB",
          "responded": false,
          "respondedDate": null,
          "message": {
            "isMember": true,
            "interest": "Competitive swimming",
            "body": "My current USMS club is disbanding at the end of the season. I'm looking for a new club in the area — I'm a competitive swimmer in the 50–54 age group. Can you tell me about your coaching staff and how you handle dual club registration?"
          }
        },
        {
          "id": "pm-012",
          "firstName": "Derek",
          "lastName": "Osei",
          "email": "derek.osei@gmail.com",
          "phone": "941-555-0266",
          "contactDate": "2026-06-15",
          "source": "CLUB",
          "responded": false,
          "respondedDate": null,
          "message": {
            "isMember": false,
            "interest": "General fitness",
            "body": "I moved to the area a few weeks ago and a neighbor mentioned your club. I'm mostly interested in staying active — I swim maybe three times a week on my own. What do your beginner-friendly practices look like?"
          }
        },
        {
          "id": "pm-001",
          "firstName": "Tom",
          "lastName": "Bradley",
          "email": "tom.bradley@gmail.com",
          "phone": "941-555-0182",
          "contactDate": "2026-07-01",
          "source": "CLUB",
          "responded": false,
          "respondedDate": null,
          "message": {
            "isMember": false,
            "interest": "Competitive swimming",
            "body": "Hi, I swam competitively in college and have been looking to get back in the water. I live about 10 minutes from your practice location. Could you let me know about tryouts or any beginner workouts for returning swimmers?"
          }
        },
        {
          "id": "pm-007",
          "firstName": "Rachel",
          "lastName": "Nguyen",
          "email": "rachel.nguyen@gmail.com",
          "phone": "813-555-0463",
          "contactDate": "2026-07-03",
          "source": "TMS",
          "responded": false,
          "respondedDate": null,
          "message": {
            "isMember": false,
            "interest": "Fitness swimming",
            "body": "I signed up for a USMS trial membership last month and have been looking for a local club to actually start swimming with. Your practice times work well for my schedule — do you have a way to try a workout before committing?"
          }
        },
        {
          "id": "pm-002",
          "firstName": "Sarah",
          "lastName": "Chen",
          "email": "sarah.chen@outlook.com",
          "phone": "941-555-0247",
          "contactDate": "2026-06-05",
          "source": "TMS",
          "responded": false,
          "respondedDate": null,
          "message": {
            "isMember": true,
            "interest": "Fitness swimming",
            "body": "I'm a current USMS member with a lapsed club affiliation. Looking for a club with early morning practices. Your schedule looks like a good fit — just wanted to connect before registering."
          }
        },
        {
          "id": "pm-003",
          "firstName": "Mike",
          "lastName": "Torres",
          "email": "mike.torres@yahoo.com",
          "phone": "",
          "contactDate": "2026-06-03",
          "source": "CLUB",
          "responded": true,
          "respondedDate": "2026-06-08",
          "message": {
            "isMember": false,
            "interest": "Open water",
            "body": "I've been doing open water swims on my own and heard your club does group training. Is that something you offer in the summer months?"
          }
        },
        {
          "id": "pm-004",
          "firstName": "Linda",
          "lastName": "Park",
          "email": "linda.park@gmail.com",
          "phone": "813-555-0391",
          "contactDate": "2026-05-28",
          "source": "TMS",
          "responded": true,
          "respondedDate": "2026-06-02",
          "message": {
            "isMember": false,
            "interest": "General fitness",
            "body": "I'm brand new to Masters swimming and not sure where to start. A friend recommended your club. Are there beginner lanes at your practices?"
          }
        },
        {
          "id": "pm-005",
          "firstName": "James",
          "lastName": "Okafor",
          "email": "james.okafor@icloud.com",
          "phone": "727-555-0614",
          "contactDate": "2026-03-15",
          "source": "CLUB",
          "responded": false,
          "respondedDate": null,
          "message": {
            "isMember": true,
            "interest": "Competitive swimming",
            "body": "I'm relocating to the area in the spring and want to find a club before I arrive. Can you tell me more about your competitive program and meet schedule for the rest of the year?"
          }
        },
        {
          "id": "pm-006",
          "firstName": "Diane",
          "lastName": "Russo",
          "email": "diane.russo@hotmail.com",
          "phone": "813-555-0728",
          "contactDate": "2026-01-10",
          "source": "TMS",
          "responded": true,
          "respondedDate": "2026-01-14",
          "message": {
            "isMember": false,
            "interest": "Triathlon training",
            "body": "I'm training for my first triathlon this spring and need to seriously improve my swim. Do you have coaches who work with triathletes, or is the club focused more on competitive pool swimming?"
          }
        }
      ]
    }
  ]
}
